random_open_port/__init__.py
random_open_port/random_open_port.py
random_open_port-0.0.2.dist-info/LICENSE
random_open_port-0.0.2.dist-info/METADATA
random_open_port-0.0.2.dist-info/WHEEL
random_open_port-0.0.2.dist-info/entry_points.txt
random_open_port-0.0.2.dist-info/top_level.txt
random_open_port-0.0.2.dist-info/RECORD
