Metadata-Version: 2.1
Name: random-open-port
Version: 0.0.2
Summary: A simple command line tool for generating a random non-affiliated port.
Home-page: https://github.com/joe-habel/random-open-port.git
Author: Joe Habel
Author-email: habeljw@gmail.com
License: MIT
Platform: UNKNOWN
Classifier: Programming Language :: Python :: 3
Classifier: License :: OSI Approved :: MIT License
Requires-Python: >=3
Requires-Dist: beautifulsoup4
